dooly/__init__.py
dooly/__version__.py
dooly/build_utils.py
dooly/dooly.py
dooly/converters/__init__.py
dooly/converters/base.py
dooly/converters/kobart_utils.py
dooly/converters/task_specific.py
dooly/models/__init__.py
dooly/models/modeling_bart.py
dooly/models/modeling_fsmt.py
dooly/models/modeling_roberta.py
dooly/models/utils/__init__.py
dooly/models/utils/modeling_heads.py
dooly/models/utils/modeling_outputs.py
dooly/models/utils/modeling_utils.py
dooly/tasks/__init__.py
dooly/tasks/consistuency_parsing.py
dooly/tasks/dependency_parsing.py
dooly/tasks/dialogue_state_tracking.py
dooly/tasks/fill_in_the_blank.py
dooly/tasks/grammatical_error_correction.py
dooly/tasks/information_retrieval.py
dooly/tasks/machine_reading_comprehension.py
dooly/tasks/machine_translation.py
dooly/tasks/named_entity_recognition.py
dooly/tasks/natural_language_inference.py
dooly/tasks/open_domain_question_answering.py
dooly/tasks/optical_character_recognition.py
dooly/tasks/paraphrase_generation.py
dooly/tasks/pos_tagging.py
dooly/tasks/question_generation.py
dooly/tasks/relation_extraction.py
dooly/tasks/semantic_role_labeling.py
dooly/tasks/semantic_textual_similarity.py
dooly/tasks/sentence_embedding.py
dooly/tasks/summarization.py
dooly/tasks/word_embedding.py
dooly/tasks/word_sense_disambiguation.py
dooly/tasks/zero_shot_classification.py
dooly/tasks/base/__init__.py
dooly/tasks/base/base.py
dooly/tasks/base/misc.py
dooly/tasks/base/seq2seq.py
dooly/tasks/base/sequence_tagging.py
dooly/tasks/base/text_classification.py
dooly/tasks/base/wikipedia2vec.py
dooly/tokenizers/__init__.py
dooly/tokenizers/base.py
dooly/tokenizers/bpe.py
dooly/tokenizers/char.py
dooly/tokenizers/hf_tokenizer.py
dooly/tokenizers/import_utils.py
dooly/tokenizers/pos_tagger.py
dooly-0.1.3.dist-info/LICENSE
dooly-0.1.3.dist-info/METADATA
dooly-0.1.3.dist-info/WHEEL
dooly-0.1.3.dist-info/top_level.txt
dooly-0.1.3.dist-info/RECORD
