Metadata-Version: 2.1
Name: dooly
Version: 0.1.3
Summary: A library that handles everything with 🤗 and supports batching to models in PORORO
Home-page: https://github.com/jinmang2/DOOLY
Author: jinmang2
Author-email: jinmang2@gmail.com
License: UNKNOWN
Platform: UNKNOWN
Classifier: Operating System :: OS Independent
Classifier: Programming Language :: Python :: 3
Classifier: Programming Language :: Python :: 3.6
Classifier: Programming Language :: Python :: 3.7
Classifier: Programming Language :: Python :: 3.8
Classifier: Programming Language :: Python :: 3.9
Classifier: License :: OSI Approved :: Apache Software License
Requires-Python: >=3.6.0
Requires-Dist: filelock
Requires-Dist: huggingface-hub (<1.0,>=0.1.0)
Requires-Dist: datasets
Requires-Dist: numpy (>=1.17)
Requires-Dist: torch (>=1.0)
Requires-Dist: packaging (>=20.0)
Requires-Dist: pyyaml (>=5.1)
Requires-Dist: regex
Requires-Dist: requests
Requires-Dist: tokenizers (!=0.11.3,>=0.11.1)
Requires-Dist: transformers (>=4.8.2)
Requires-Dist: tqdm (>=4.27)
Requires-Dist: kss (>=3.4.2)
Requires-Dist: nltk
Requires-Dist: dataclasses ; python_version < "3.7"
Provides-Extra: all
Requires-Dist: fugashi (>=1.0) ; extra == 'all'
Requires-Dist: ipadic (<2.0,>=1.0.0) ; extra == 'all'
Requires-Dist: jieba ; extra == 'all'
Requires-Dist: whoosh ; extra == 'all'
Requires-Dist: black (~=22.0) ; extra == 'all'
Requires-Dist: flake8 (>=3.8.3) ; extra == 'all'
Provides-Extra: convert
Requires-Dist: pororo ; extra == 'convert'
Requires-Dist: boto3 ; extra == 'convert'
Provides-Extra: ja
Requires-Dist: fugashi (>=1.0) ; extra == 'ja'
Requires-Dist: ipadic (<2.0,>=1.0.0) ; extra == 'ja'
Provides-Extra: pororo
Requires-Dist: fugashi (>=1.0) ; extra == 'pororo'
Requires-Dist: ipadic (<2.0,>=1.0.0) ; extra == 'pororo'
Requires-Dist: jieba ; extra == 'pororo'
Requires-Dist: whoosh ; extra == 'pororo'
Requires-Dist: black (~=22.0) ; extra == 'pororo'
Requires-Dist: flake8 (>=3.8.3) ; extra == 'pororo'
Requires-Dist: pororo ; extra == 'pororo'
Requires-Dist: boto3 ; extra == 'pororo'
Provides-Extra: quality
Requires-Dist: black (~=22.0) ; extra == 'quality'
Requires-Dist: flake8 (>=3.8.3) ; extra == 'quality'
Provides-Extra: search
Requires-Dist: whoosh ; extra == 'search'
Provides-Extra: zh
Requires-Dist: jieba ; extra == 'zh'
